candlecraft/__init__.py
candlecraft/api.py
candlecraft/models.py
candlecraft/providers.py
candlecraft/utils.py
candlecraft-0.1.4.dist-info/licenses/LICENSE
candlecraft-0.1.4.dist-info/METADATA
candlecraft-0.1.4.dist-info/WHEEL
candlecraft-0.1.4.dist-info/top_level.txt
candlecraft-0.1.4.dist-info/RECORD
