Metadata-Version: 2.4
Name: candlecraft
Version: 0.1.4
Summary: A clean, reusable Python library for fetching OHLCV data from multiple providers (Binance, Twelve Data) with flexible provider selection
Author: AlfredAlpino
Maintainer: AlfredAlpino
License: MIT
Project-URL: Homepage, https://github.com/alfredalpino/Candlecraft
Project-URL: Documentation, https://github.com/alfredalpino/Candlecraft#candlecraft-library
Project-URL: Repository, https://github.com/alfredalpino/Candlecraft
Project-URL: Issues, https://github.com/alfredalpino/Candlecraft/issues
Keywords: ohlcv,crypto,forex,equity,trading,binance,twelvedata,financial-data
Classifier: Development Status :: 3 - Alpha
Classifier: Intended Audience :: Developers
Classifier: Intended Audience :: Financial and Insurance Industry
Classifier: License :: OSI Approved :: MIT License
Classifier: Operating System :: OS Independent
Classifier: Programming Language :: Python :: 3
Classifier: Programming Language :: Python :: 3.10
Classifier: Programming Language :: Python :: 3.11
Classifier: Programming Language :: Python :: 3.12
Classifier: Topic :: Office/Business :: Financial :: Investment
Classifier: Topic :: Software Development :: Libraries :: Python Modules
Requires-Python: >=3.10
License-File: LICENSE
Requires-Dist: python-binance>=1.0.0
Requires-Dist: websocket-client>=1.6.0
Requires-Dist: twelvedata>=1.0.0
Requires-Dist: pandas>=2.0.0
Provides-Extra: dev
Requires-Dist: pytest>=7.0.0; extra == "dev"
Requires-Dist: pytest-cov>=4.0.0; extra == "dev"
Dynamic: license-file
